mdformat_frontmatter/__init__.py
mdformat_frontmatter/plugin.py
mdformat_frontmatter-2.0.10.dist-info/entry_points.txt
mdformat_frontmatter-2.0.10.dist-info/licenses/LICENSE
mdformat_frontmatter-2.0.10.dist-info/WHEEL
mdformat_frontmatter-2.0.10.dist-info/METADATA
mdformat_frontmatter-2.0.10.dist-info/RECORD
