Metadata-Version: 2.4
Name: mdformat_frontmatter
Version: 2.0.10
Summary: An mdformat plugin for parsing / ignoring frontmatter.
Keywords: mdformat,markdown,markdown-it
Author-email: Chris Butler <chris@thebutlers.me>
Requires-Python: >=3.7
Classifier: Intended Audience :: Developers
Classifier: License :: OSI Approved :: MIT License
Classifier: Programming Language :: Python :: 3
Classifier: Topic :: Software Development :: Libraries :: Python Modules
License-File: LICENSE
Requires-Dist: mdformat >=0.7.16
Requires-Dist: mdit-py-plugins >=0.4.0
Requires-Dist: ruamel.yaml
Requires-Dist: pre-commit ; extra == "dev"
Requires-Dist: python-semantic-release >=8.3.0 ; extra == "dev"
Requires-Dist: flit >= 3.9 ; extra == "dev"
Requires-Dist: pytest>=7.3 ; extra == "test"
Requires-Dist: coverage ; extra == "test"
Requires-Dist: pytest-cov ; extra == "test"
Project-URL: Changelog, https://github.com/butler54/mdformat-frontmatter/blob/main/CHANGELOG.md
Project-URL: Source, https://github.com/butler54/mdformat-frontmatter
Provides-Extra: dev
Provides-Extra: test
